naboo/__init__.py
naboo/db.py
naboo-0.1.19.dist-info/METADATA
naboo-0.1.19.dist-info/WHEEL
naboo-0.1.19.dist-info/RECORD
