Metadata-Version: 2.3
Name: naboo
Version: 0.1.19
Summary: 
License: MIT
Author: Brendan Doms
Requires-Python: >=3.12
Classifier: License :: OSI Approved :: MIT License
Classifier: Programming Language :: Python :: 3
Classifier: Programming Language :: Python :: 3.12
Classifier: Programming Language :: Python :: 3.13
Requires-Dist: asyncpg (==0.30.0)
